palcodeinfra/__init__.py
palcodeinfra/baseapi.py
palcodeinfra/database.py
palcodeinfra/logger.py
palcodeinfra/requestidmiddleware.py
palcodeinfra/requestloggermiddleware.py
palcodeinfra/secretmanager.py
palcodeinfra/tenantidmiddleware.py
palcodeinfra/tokenmiddleware.py
palcodeinfra/useridmiddleware.py
palcodeinfra-0.1.12.dist-info/METADATA
palcodeinfra-0.1.12.dist-info/WHEEL
palcodeinfra-0.1.12.dist-info/top_level.txt
palcodeinfra-0.1.12.dist-info/RECORD
