Metadata-Version: 2.2
Name: palcodeinfra
Version: 0.1.12
Summary: A package containing infrastructure functionalities to build apis
Home-page: https://github.com/Palcode-ai/palcode-infrastructure
Author: Palcode
Author-email: palcode@palcode.ai
Classifier: Programming Language :: Python :: 3.12
Classifier: License :: OSI Approved :: MIT License
Classifier: Operating System :: OS Independent
Requires-Python: >=3.12
Requires-Dist: sqlalchemy
Requires-Dist: pydantic
Requires-Dist: pydantic-settings
Requires-Dist: psycopg
Requires-Dist: boto3
Requires-Dist: pyyaml
Dynamic: author
Dynamic: author-email
Dynamic: classifier
Dynamic: description
Dynamic: description-content-type
Dynamic: home-page
Dynamic: requires-dist
Dynamic: requires-python
Dynamic: summary
